easywrite.py
easywrite-1.5.0.dist-info/METADATA
easywrite-1.5.0.dist-info/WHEEL
easywrite-1.5.0.dist-info/top_level.txt
easywrite-1.5.0.dist-info/RECORD
