Metadata-Version: 2.1
Name: easywrite
Version: 1.5.0
Summary: A Python module for easy text output with colors
Home-page: https://github.com/skxllhead/easywrite
Author: skxllhead
Classifier: Programming Language :: Python :: 3
Classifier: License :: OSI Approved :: MIT License
Classifier: Operating System :: OS Independent
